{
    "server_addr": "127.0.0.1",
    "server_port": 7000,
    "log_level": "info",
    "auth_token": "my-secret-token-123",
    "reconnect": true,
    "reconnect_max_retries": 5,
    "reconnect_base_delay": 1,
    "reconnect_max_delay": 30,
    "tls": true,
    "tls_insecure": true,
    "data_port": 7001,
    "proxies": [
        {
            "name": "web",
            "type": "tcp",
            "local_ip": "127.0.0.1",
            "local_port": 8086,
            "remote_port": 9096,
            "enabled": true
        },
        {
            "name": "ftp_test",
            "type": "ftp",
            "local_ip": "127.0.0.1",
            "local_port": 2122,
            "remote_port": 8022
        }
    ]
}